opuscleaner/__about__.py
opuscleaner/__init__.py
opuscleaner/_util.py
opuscleaner/categories.py
opuscleaner/clean.py
opuscleaner/col.py
opuscleaner/config.py
opuscleaner/datasets.py
opuscleaner/download.py
opuscleaner/filtering.py
opuscleaner/logging.py
opuscleaner/opusfilter_compat.py
opuscleaner/sample.py
opuscleaner/server.py
opuscleaner/threshold.py
opuscleaner/filters/__init__.py
opuscleaner/filters/alpha_ratio.json
opuscleaner/filters/alpha_ratio.py
opuscleaner/filters/bicleaner_hardrules.json
opuscleaner/filters/bifixer.json
opuscleaner/filters/bifixer_dedupe.py
opuscleaner/filters/clean_common.py
opuscleaner/filters/currency_mismatch.json
opuscleaner/filters/currency_mismatch.py
opuscleaner/filters/deescape-special-chars.json
opuscleaner/filters/deescape-special-chars.perl
opuscleaner/filters/deescape_tsv.json
opuscleaner/filters/deescape_tsv.py
opuscleaner/filters/detokenizer.json
opuscleaner/filters/detokenizer.perl
opuscleaner/filters/fasttext_filter.json
opuscleaner/filters/fasttext_filter.py
opuscleaner/filters/fix_elitr_eca.json
opuscleaner/filters/fix_elitr_eca.py
opuscleaner/filters/fix_quotes.json
opuscleaner/filters/fix_quotes.py
opuscleaner/filters/fix_sent_final_punct.json
opuscleaner/filters/fix_sent_final_punct.py
opuscleaner/filters/fix_un_chinese.json
opuscleaner/filters/fix_un_chinese.py
opuscleaner/filters/fix_wiki.json
opuscleaner/filters/fix_wiki.py
opuscleaner/filters/langid.json
opuscleaner/filters/langid.py
opuscleaner/filters/langid_heliport.json
opuscleaner/filters/langid_heliport.py
opuscleaner/filters/laser_similarity.json
opuscleaner/filters/laser_similarity.py
opuscleaner/filters/max_length.json
opuscleaner/filters/max_length.py
opuscleaner/filters/max_word_length.json
opuscleaner/filters/max_word_length.py
opuscleaner/filters/normalize_whitespace.json
opuscleaner/filters/normalize_whitespace.py
opuscleaner/filters/num_mismatch.json
opuscleaner/filters/num_mismatch.py
opuscleaner/filters/regexp.json
opuscleaner-0.7.1.dist-info/METADATA
opuscleaner-0.7.1.dist-info/WHEEL
opuscleaner-0.7.1.dist-info/entry_points.txt
opuscleaner-0.7.1.dist-info/RECORD
