Metadata-Version: 2.4
Name: opuscleaner
Version: 0.7.1
Project-URL: Documentation, https://github.com/hplt-project/opuscleaner#readme
Project-URL: Issues, https://github.com/hplt-project/opuscleaner/issues
Project-URL: Source, https://github.com/hplt-project/opuscleaner
Author-email: Jelmer van der Linde <jelmer@ikhoefgeen.nl>
License-Expression: MIT
Classifier: Development Status :: 4 - Beta
Classifier: Programming Language :: Python
Classifier: Programming Language :: Python :: 3.9
Classifier: Programming Language :: Python :: 3.10
Classifier: Programming Language :: Python :: 3.11
Classifier: Programming Language :: Python :: Implementation :: CPython
Classifier: Programming Language :: Python :: Implementation :: PyPy
Requires-Python: >=3.9
Requires-Dist: babel==2.17.0
Requires-Dist: fastapi==0.78.0
Requires-Dist: pyyaml>=6.0.1
Requires-Dist: uvicorn==0.20.0
Requires-Dist: xxhash==3.2.0
Provides-Extra: all
Requires-Dist: babel; extra == 'all'
Requires-Dist: bicleaner; extra == 'all'
Requires-Dist: bifixer; extra == 'all'
Requires-Dist: fasttext; extra == 'all'
Requires-Dist: fugashi[unidic-lite]==1.1.2; extra == 'all'
Requires-Dist: hanziconv==0.3.2; extra == 'all'
Requires-Dist: iso639-lang==2.6.3; extra == 'all'
Requires-Dist: laserembeddings[ja,zh]==1.1.2; extra == 'all'
Requires-Dist: more-itertools; extra == 'all'
Requires-Dist: opusfilter==2.6.0; extra == 'all'
Requires-Dist: pycld2==0.41; extra == 'all'
Requires-Dist: requests; extra == 'all'
Requires-Dist: sacremoses; extra == 'all'
Requires-Dist: spacy-pkuseg; extra == 'all'
